ndb_drf/__init__.py
ndb_drf/ndb_generics.py
ndb_drf/ndb_mixins.py
ndb_drf/ndb_serializers.py
ndb_drf/ndb_viewsets.py
ndb_drf/utils.py
ndb_drf-0.1.2.dist-info/LICENSE
ndb_drf-0.1.2.dist-info/METADATA
ndb_drf-0.1.2.dist-info/WHEEL
ndb_drf-0.1.2.dist-info/top_level.txt
ndb_drf-0.1.2.dist-info/RECORD
